rmind/__init__.py
rmind/py.typed
rmind-0.1.0.dist-info/licenses/LICENSE
rmind-0.1.0.dist-info/METADATA
rmind-0.1.0.dist-info/WHEEL
rmind-0.1.0.dist-info/top_level.txt
rmind-0.1.0.dist-info/RECORD
